mypushover/__init__.py
mypushover/__main__.py
mypushover/_mypushover.py
mypushover/certd.py
mypushover-0.0.8.dist-info/LICENSE
mypushover-0.0.8.dist-info/METADATA
mypushover-0.0.8.dist-info/WHEEL
mypushover-0.0.8.dist-info/entry_points.txt
mypushover-0.0.8.dist-info/top_level.txt
mypushover-0.0.8.dist-info/RECORD
