Metadata-Version: 2.1
Name: mypushover
Version: 0.0.8
Home-page: https://github.com/leeyang1991/mypushover
Author: Yang Li
Author-email: leeyang1991@gmail.com
Requires-Python: >=3
License-File: LICENSE
Requires-Dist: icmplib
Requires-Dist: requests
Requires-Dist: outdated
